YewZhongwenWendangFix1/README.md
YewZhongwenWendangFix1/__init__.py
YewZhongwenWendangFix1/__main__.py
YewZhongwenWendangFix1/file.epub
YewZhongwenWendangFix1/index.html
YewZhongwenWendangFix1/css/__init__.py
YewZhongwenWendangFix1/css/annotations.css
YewZhongwenWendangFix1/css/main.css
YewZhongwenWendangFix1/css/normalize.css
YewZhongwenWendangFix1/css/popup.css
YewZhongwenWendangFix1/font/__init__.py
YewZhongwenWendangFix1/font/fontello.eot
YewZhongwenWendangFix1/font/fontello.svg
YewZhongwenWendangFix1/font/fontello.ttf
YewZhongwenWendangFix1/font/fontello.woff
YewZhongwenWendangFix1/img/__init__.py
YewZhongwenWendangFix1/img/annotator-glyph-sprite.png
YewZhongwenWendangFix1/img/annotator-icon-sprite.png
YewZhongwenWendangFix1/img/apple-touch-icon.png
YewZhongwenWendangFix1/img/cancelfullscreen.png
YewZhongwenWendangFix1/img/close.png
YewZhongwenWendangFix1/img/fullscreen.png
YewZhongwenWendangFix1/img/loader.gif
YewZhongwenWendangFix1/img/menu-icon.png
YewZhongwenWendangFix1/img/save.png
YewZhongwenWendangFix1/img/saved.png
YewZhongwenWendangFix1/img/settings-s.png
YewZhongwenWendangFix1/img/settings.png
YewZhongwenWendangFix1/img/star.png
YewZhongwenWendangFix1/js/__init__.py
YewZhongwenWendangFix1/js/epub.js
YewZhongwenWendangFix1/js/epub.min.js
YewZhongwenWendangFix1/js/epub.min.map
YewZhongwenWendangFix1/js/hooks.min.js
YewZhongwenWendangFix1/js/hooks.min.map
YewZhongwenWendangFix1/js/reader.js
YewZhongwenWendangFix1/js/reader.js.map
YewZhongwenWendangFix1/js/reader.min.js
YewZhongwenWendangFix1/js/reader.min.map
YewZhongwenWendangFix1/js/hooks/__init__.py
YewZhongwenWendangFix1/js/hooks/extensions/__init__.py
YewZhongwenWendangFix1/js/hooks/extensions/highlight.js
YewZhongwenWendangFix1/js/libs/__init__.py
YewZhongwenWendangFix1/js/libs/jquery.min.js
YewZhongwenWendangFix1/js/libs/localforage.min.js
YewZhongwenWendangFix1/js/libs/screenfull.js
YewZhongwenWendangFix1/js/libs/screenfull.min.js
YewZhongwenWendangFix1/js/libs/zip.min.js
yew_zhongwen_wendang_fix1-2025.3.25.0.dist-info/METADATA
yew_zhongwen_wendang_fix1-2025.3.25.0.dist-info/WHEEL
yew_zhongwen_wendang_fix1-2025.3.25.0.dist-info/entry_points.txt
yew_zhongwen_wendang_fix1-2025.3.25.0.dist-info/top_level.txt
yew_zhongwen_wendang_fix1-2025.3.25.0.dist-info/RECORD
